[
  {
    "timestamp": "2025-06-29T21:43:42.227369",
    "event": "Starting WebSocket connection",
    "data": null
  },
  {
    "timestamp": "2025-06-29T21:43:42.260783",
    "event": "WebSocket connected",
    "data": null
  },
  {
    "timestamp": "2025-06-29T21:43:42.260850",
    "event": "Sent client_init",
    "data": {
      "type": "client_init",
      "data": {
        "userAgent": "Daemon Bridge Tracer",
        "url": "python://trace",
        "timestamp": "2025-06-29T21:43:42.260794"
      }
    }
  },
  {
    "timestamp": "2025-06-29T21:43:42.261532",
    "event": "Received connection_confirmed",
    "data": {
      "type": "connection_confirmed",
      "data": {
        "clientId": "client_1751251422260_apt0meorn",
        "server": "websocket-server",
        "version": "1.0.0",
        "daemon": true,
        "browserState": {
          "hasActiveConnections": true,
          "connectedClients": [],
          "debugMode": false
        }
      },
      "timestamp": "2025-06-30T02:43:42.261Z"
    }
  },
  {
    "timestamp": "2025-06-29T21:43:42.261554",
    "event": "Requesting daemon status via get_stats",
    "data": null
  },
  {
    "timestamp": "2025-06-29T21:43:42.262149",
    "event": "Daemon connector status",
    "data": {
      "connected": null,
      "commands_available": null,
      "registered_daemons": [],
      "total_message_types": null
    }
  },
  {
    "timestamp": "2025-06-29T21:43:42.262162",
    "event": "Requesting available capabilities",
    "data": null
  },
  {
    "timestamp": "2025-06-29T21:43:42.262472",
    "event": "Available capabilities",
    "data": {
      "type": "get_stats_response",
      "data": {
        "server": {
          "name": "websocket-server",
          "version": "1.0.0",
          "status": {
            "name": "websocket-server",
            "version": "1.0.0",
            "status": "running",
            "pid": 82764,
            "uptime": 25494,
            "memoryUsage": {
              "rss": 114802688,
              "heapTotal": 11190272,
              "heapUsed": 9630952,
              "external": 3918372,
              "arrayBuffers": 74673
            },
            "cpuUsage": {
              "user": 474010,
              "system": 67647
            },
            "startTime": "2025-06-30T02:43:16.768Z"
          },
          "uptime": 25494,
          "port": 9000,
          "host": "localhost"
        },
        "connections": {
          "totalClients": 1,
          "maxClients": 100,
          "averageConnectionTime": 2,
          "oldestConnection": 1751251422260,
          "heartbeatEnabled": true,
          "heartbeatInterval": 30000
        },
        "browserConnections": {
          "hasActiveConnections": true,
          "connectedClients": 0,
          "debugMode": false,
          "clients": []
        },
        "daemonConnector": {
          "connected": true,
          "commandsAvailable": 6
        },
        "dynamicRouter": {
          "registeredDaemons": 1,
          "daemons": [
            {
              "name": "websocket-server",
              "capabilities": [
                "websocket-server",
                "client-management",
                "api-endpoints",
                "css-service"
              ],
              "messageTypes": [
                "ping",
                "pong",
                "get_stats",
                "get_clients",
                "get_capabilities",
                "render_request",
                "switch_engine",
                "execute_command",
                "broadcast_message",
                "send_message",
                "tabRegister",
                "get_component_css"
              ]
            }
          ],
          "totalMessageTypes": 12
        },
        "registeredDaemons": []
      },
      "timestamp": "2025-06-30T02:43:42.262Z",
      "clientId": "client_1751251422260_apt0meorn",
      "processedBy": "websocket-server"
    }
  },
  {
    "timestamp": "2025-06-29T21:43:42.262544",
    "event": "Attempting command execution: health",
    "data": null
  },
  {
    "timestamp": "2025-06-29T21:43:42.262576",
    "event": "Sent execute_command",
    "data": {
      "type": "execute_command",
      "data": {
        "command": "health",
        "args": {}
      },
      "timestamp": "2025-06-29T21:43:42.262546",
      "clientId": "client_1751251422260_apt0meorn"
    }
  },
  {
    "timestamp": "2025-06-29T21:43:42.262680",
    "event": "Command execution response",
    "data": {
      "type": "get_capabilities_response",
      "data": {
        "capabilities": [
          "websocket-server",
          "client-management",
          "api-endpoints",
          "css-service"
        ]
      },
      "timestamp": "2025-06-30T02:43:42.262Z",
      "clientId": "client_1751251422260_apt0meorn",
      "processedBy": "websocket-server"
    }
  }
]